darbird
