Metadata-Version: 2.1
Name: darbird
Version: 1.0.1
Summary: Official Darbird Python SDK
Home-page: https://github.com/darbird/darbird-python
Author: Darbird
Author-email: developers@darbird.com
License: MIT
Download-URL: https://github.com/darbird/darbird-python/archive/1.1.tar.gz/
Keywords: voice sms sender_id darbird
Platform: UNKNOWN
Requires-Python: >=2.7.10
